pylitterbot/__init__.py
pylitterbot/account.py
pylitterbot/activity.py
pylitterbot/enums.py
pylitterbot/event.py
pylitterbot/exceptions.py
pylitterbot/pet.py
pylitterbot/py.typed
pylitterbot/robot/__init__.py
pylitterbot/robot/feederrobot.py
pylitterbot/robot/litterrobot.py
pylitterbot/robot/litterrobot3.py
pylitterbot/robot/litterrobot4.py
pylitterbot/robot/models.py
pylitterbot/session.py
pylitterbot/utils.py
pylitterbot/ws_monitor.py
pylitterbot-2025.0.0.dist-info/METADATA
pylitterbot-2025.0.0.dist-info/WHEEL
pylitterbot-2025.0.0.dist-info/licenses/LICENSE
pylitterbot-2025.0.0.dist-info/RECORD
