Metadata-Version: 2.4
Name: pylitterbot
Version: 2025.0.0
Summary: Python package for controlling Whisker automatic robots.
License-Expression: MIT
License-File: LICENSE
Keywords: Whisker,Litter-Robot,Feeder-Robot,litter box,pet feeder,asynchronous
Author: Nathan Spencer
Author-email: natekspencer@gmail.com
Requires-Python: >=3.10
Classifier: Programming Language :: Python :: 3
Classifier: Programming Language :: Python :: 3.10
Classifier: Programming Language :: Python :: 3.11
Classifier: Programming Language :: Python :: 3.12
Classifier: Programming Language :: Python :: 3.13
Classifier: Programming Language :: Python :: 3.14
Requires-Dist: aiohttp (>=3.8.1)
Requires-Dist: deepdiff (>=6.2.1)
Requires-Dist: pycognito (>=2024.2.0)
Requires-Dist: pyjwt (>=2.7.0)
Project-URL: Homepage, https://github.com/natekspencer/pylitterbot
Project-URL: Repository, https://github.com/natekspencer/pylitterbot
